LICENSE.rst
README.rst
setup.py
sports/__init__.py
sports/apps.py
sports/models.py
sports/urls.py
sports/utils.py
sports/admin/__init__.py
sports/admin/mixins.py
sports/admin/sports.py
sports/management/__init__.py
sports/management/commands/__init__.py
sports/management/commands/import_club.py
sports/management/commands/import_data.py
sports/management/commands/import_ncaa_season.py
sports/management/commands/import_ncaa_teams.py
sports/management/commands/import_nfl_season.py
sports/management/commands/import_nfl_teams.py
sports/management/commands/import_teams.py
sports/management/commands/reset_app.py
sports/management/commands/score_contest.py
sports/management/commands/simulate_season_picks.py
sports/management/commands/test_initial_credentials.py
sports/migrations/0001_initial.py
sports/migrations/0002_team_alias.py
sports/migrations/0003_venue_address.py
sports/migrations/0004_sport.py
sports/migrations/0005_alter_sport_options_league.py
sports/migrations/0006_conference_league.py
sports/migrations/0007_alter_conference_league.py
sports/migrations/0008_player.py
sports/migrations/0009_player_player_id.py
sports/migrations/0010_alter_player_options_player_birth_date_player_height_and_more.py
sports/migrations/0011_alter_player_height_alter_player_jersey_number_and_more.py
sports/migrations/0012_season_season_id_alter_season_label.py
sports/migrations/0013_rename_season_name_season_name_and_more.py
sports/migrations/0014_season_league.py
sports/migrations/0015_season_hash.py
sports/migrations/0016_alter_venue_address_alter_venue_city_and_more.py
sports/migrations/0017_remove_gameperiod_sport_radar_period_id_and_more.py
sports/migrations/0018_gameperiod_label.py
sports/migrations/__init__.py
sports/templatetags/__init__.py
sports/templatetags/sports_tags.py
sports/views/__init__.py
sports/views/decorators.py
sports/views/forms.py
sports/views/sports.py
sportspicker.egg-info/PKG-INFO
sportspicker.egg-info/SOURCES.txt
sportspicker.egg-info/dependency_links.txt
sportspicker.egg-info/requires.txt
sportspicker.egg-info/top_level.txt
sportsuser/__init__.py
sportsuser/admin.py
sportsuser/apps.py
sportsuser/models.py
sportsuser/tests.py
